hardyweinberg_equilibrium/__init__.py
hardyweinberg_equilibrium/config.py
hardyweinberg_equilibrium/main.py
hardyweinberg_equilibrium-0.1.3.post20230611.dist-info/LICENSE
hardyweinberg_equilibrium-0.1.3.post20230611.dist-info/METADATA
hardyweinberg_equilibrium-0.1.3.post20230611.dist-info/WHEEL
hardyweinberg_equilibrium-0.1.3.post20230611.dist-info/entry_points.txt
hardyweinberg_equilibrium-0.1.3.post20230611.dist-info/top_level.txt
hardyweinberg_equilibrium-0.1.3.post20230611.dist-info/RECORD
