Metadata-Version: 2.1
Name: hardyweinberg-equilibrium
Version: 0.1.3.post20230611
Summary: Hardy-Weinberg Equilibrium Calculator. Calculates the expected genotype frequencies based on the allele frequencies of a population in Hardy-Weinberg equilibrium.
Author: Dellius Alexander
Author-email: info@hyfisolutions.com
Maintainer: info@hyfisolutions.com
Maintainer-email: info@hyfisolutions.com
License: LICENSE
Classifier: Development Status :: 5 - Production/Stable
Classifier: Intended Audience :: Developers
Classifier: Operating System :: OS Independent
Classifier: Programming Language :: Python
Classifier: Programming Language :: Python :: 2.7
Classifier: Programming Language :: Python :: 3.4
Classifier: Programming Language :: Python :: 3.5
Classifier: Programming Language :: Python :: 3.6
Classifier: Programming Language :: Python :: 3.7
Classifier: Programming Language :: Python :: Implementation :: CPython
Classifier: Programming Language :: Python :: Implementation :: PyPy
License-File: LICENSE
Requires-Dist: sympy
Requires-Dist: numpy
Requires-Dist: matplotlib
Requires-Dist: pandas
